sqlalchemy_serializer_meta/__init__.py
sqlalchemy_serializer_meta/serializer.py
sqlalchemy_serializer_meta/validator.py
sqlalchemy_serializer_meta-0.3.0.dist-info/LICENSE
sqlalchemy_serializer_meta-0.3.0.dist-info/METADATA
sqlalchemy_serializer_meta-0.3.0.dist-info/WHEEL
sqlalchemy_serializer_meta-0.3.0.dist-info/top_level.txt
sqlalchemy_serializer_meta-0.3.0.dist-info/RECORD
