Metadata-Version: 2.1
Name: sqlalchemy_serializer_meta
Version: 0.3.0
Summary: A simple serializer for SQLAlchemy models and Flask Models
Home-page: https://github.com/Wehda23/sqlalchemy_serializer_meta
Author: Waheed Khaled Elhariri
Author-email: waheedkhaled95@gmail.com
License: MIT
Keywords: sqlalchemy serializer pydantic flask
Classifier: Development Status :: 4 - Beta
Classifier: Intended Audience :: Developers
Classifier: License :: OSI Approved :: MIT License
Classifier: Programming Language :: Python :: 3.9
Classifier: Programming Language :: Python :: 3.10
Classifier: Programming Language :: Python :: 3.11
Classifier: Programming Language :: Python :: 3.12
License-File: LICENSE
Requires-Dist: sqlalchemy
Requires-Dist: pydantic ==2.7.4
Requires-Dist: pydantic-core ==2.18.4
